{
  "cities": [
    {
      "cityName": "Manila",
      "country": "Philippines (the)",
      "emoji": "🇵🇭",
      "date": "2023-12-13T14:45:33.606Z",
      "notes": "",
      "position": {
        "lat": "14.514877720098836",
        "lng": "121.04066848754884"
      },
      "id": 73930387
    },
    {
      "cityName": "Manila",
      "country": "Philippines (the)",
      "emoji": "🇵🇭",
      "date": "2023-12-13T15:40:18.415Z",
      "notes": "",
      "position": {
        "lat": "14.540966816684424",
        "lng": "121.0224723815918"
      },
      "id": 73930388
    },
    {
      "cityName": "San Antonio",
      "country": "Philippines (the)",
      "emoji": "🇵🇭",
      "date": "2023-12-13T15:40:48.890Z",
      "notes": "",
      "position": {
        "lat": "15.306041821392899",
        "lng": "120.84789276123048"
      },
      "id": 73930389
    }
  ]
}
